htrvx/__init__.py
htrvx/cli.py
htrvx/testing.py
htrvx/zones.py
htrvx/schemas/2839a369e9159a3aaa13640bc0a6bd6b36b4e8d05558d6f17c1bcaa8d99b2944.xsd
htrvx/schemas/2c2add4986e9994145c8d31814e9424735be08acde9129daa35c7bd7e20a7e05.xsd
htrvx/schemas/64785a10cba3515bfb5e458dd66e8d3a410ca3ac17ba5ead6867f76a8c35f158.xsd
htrvx/schemas/7711274c649d142b6f7113b8616a5f150980509a924a6b1bf083abdec333a233.xsd
htrvx/schemas/7b14023d5b668ec373381866662be92b6654bb215db697d0621200a60ecc902a.xsd
htrvx/schemas/__init__.py
htrvx/schemas/alto4.xsd
htrvx/schemas/bb4682843b206c99cf51ff1ab35aaded171203cf99c40fd73987b3828b27015b.xsd
htrvx/schemas/ccaffbbe8477a9484987d8891dcb7d2419160d1ae7449b7318d889bd7847c0ee.xsd
htrvx/schemas/e09d4537a85de5a741ebb63d8876008b9be1d793340552823f6820295d5259db.xsd
htrvx/schemas/e23806059815995d78978c4b84b7cda8d0ce23212600ac9ec14c2e64b1c23e12.xsd
htrvx/schemas/f6604b4f9377fdec09ecbbec4ff2c2dbbe661cd61dcd502b911a5c509f2438f1.xsd
htrvx/schemas/page2019.xsd
htrvx-0.0.19.dist-info/LICENSE
htrvx-0.0.19.dist-info/METADATA
htrvx-0.0.19.dist-info/WHEEL
htrvx-0.0.19.dist-info/entry_points.txt
htrvx-0.0.19.dist-info/top_level.txt
htrvx-0.0.19.dist-info/RECORD
