Metadata-Version: 2.1
Name: htrvx
Version: 0.0.19
Summary: HTRVX, HTR Validation with XSD
Home-page: https://github.com/htr-united/htrvx
Author: Thibault Clérice & Ariane Pinche
License: MIT
Platform: UNKNOWN
Classifier: License :: OSI Approved :: MIT License
Classifier: Programming Language :: Python
Classifier: Programming Language :: Python :: 3
Classifier: Programming Language :: Python :: 3.6
Classifier: Programming Language :: Python :: Implementation :: CPython
Classifier: Programming Language :: Python :: Implementation :: PyPy
Classifier: Topic :: Text Processing :: Linguistic
Requires-Python: >=3.6.0
Requires-Dist: click (<=9.0)
Requires-Dist: lxml
Requires-Dist: requests
Requires-Dist: typing-extensions ; python_version<'3.8'
